.gitignore
LICENSE
README.rst
setup.cfg
setup.py
lrcloud/__init__.py
lrcloud/__main__.py
lrcloud/config_parser.py
lrcloud/metafile.py
lrcloud/test.py
lrcloud/util.py
lrcloud.egg-info/PKG-INFO
lrcloud.egg-info/SOURCES.txt
lrcloud.egg-info/dependency_links.txt
lrcloud.egg-info/entry_points.txt
lrcloud.egg-info/top_level.txt