Metadata-Version: 1.1
Name: lrcloud
Version: 0.1.1.post4
Summary: Adobe Lightroom cloud support
Home-page: https://github.com/madsbk/lrcloud
Author: Mads R. B. Kristensen
Author-email: madsbk@gmail.com
License: GPL
Keywords: Lightroom Cloud
Platform: UNKNOWN
Classifier: Development Status :: 3 - Alpha
Classifier: Intended Audience :: End Users/Desktop
Classifier: Topic :: Multimedia
Classifier: License :: OSI Approved :: GNU General Public License (GPL)
Classifier: Programming Language :: Python :: 2.7
Classifier: Programming Language :: Python :: 3
